examplepkglarkintuckerllc/__init__.py
examplepkglarkintuckerllc/__main__.py
examplepkglarkintuckerllc/example_module.py
examplepkglarkintuckerllc-0.0.3.dist-info/LICENSE
examplepkglarkintuckerllc-0.0.3.dist-info/METADATA
examplepkglarkintuckerllc-0.0.3.dist-info/WHEEL
examplepkglarkintuckerllc-0.0.3.dist-info/top_level.txt
examplepkglarkintuckerllc-0.0.3.dist-info/RECORD
